bootwrap/__init__.py
bootwrap/auth.py
bootwrap/generic.css
bootwrap/generic.js
bootwrap/menu.py
bootwrap/page.py
bootwrap/components/__init__.py
bootwrap/components/anchor.py
bootwrap/components/badge.py
bootwrap/components/base.py
bootwrap/components/button.py
bootwrap/components/deck.py
bootwrap/components/dialog.py
bootwrap/components/form.py
bootwrap/components/icon.py
bootwrap/components/image.py
bootwrap/components/javascript.py
bootwrap/components/link.py
bootwrap/components/list.py
bootwrap/components/navigation.py
bootwrap/components/panel.py
bootwrap/components/separator.py
bootwrap/components/table.py
bootwrap/components/text.py
bootwrap/components/toast.py
bootwrap/components/utils.py
bootwrap-1.2.9.dist-info/licenses/LICENSE
demo/__init__.py
demo/demo_app.py
demo/demo_components.py
demo/demo_stock.py
demo/demo_user.py
docs/__init__.py
docs/doc_app.py
docs/doc_generator.py
bootwrap-1.2.9.dist-info/METADATA
bootwrap-1.2.9.dist-info/WHEEL
bootwrap-1.2.9.dist-info/top_level.txt
bootwrap-1.2.9.dist-info/RECORD
