Metadata-Version: 2.4
Name: bootwrap
Version: 1.2.9
Summary: Package for rapid development of web-based user interfaces.
Home-page: https://github.com/mmgalushka/bootwrap
Author: Mykola Galushka
Author-email: mm.galushka@gmail.com
Project-URL: Bug Tracker, https://github.com/mmgalushka/bootwrap/issues
Classifier: Intended Audience :: Developers
Classifier: License :: OSI Approved :: MIT License
Classifier: Operating System :: OS Independent
Classifier: Programming Language :: Python :: 3
Requires-Python: >=3.6
License-File: LICENSE
Dynamic: author
Dynamic: author-email
Dynamic: classifier
Dynamic: description
Dynamic: description-content-type
Dynamic: home-page
Dynamic: license-file
Dynamic: project-url
Dynamic: requires-python
Dynamic: summary
